digout/__init__.py
digout/py.typed
digout/_moore/__init__.py
digout/_moore/catalog.py
digout/_moore/digi2mdf.py
digout/_moore/digi2root.py
digout/_moore/options.py
digout/_utils/__init__.py
digout/_utils/debug.py
digout/_utils/envvar.py
digout/_utils/format.py
digout/_utils/ioyaml.py
digout/_utils/logging.py
digout/_utils/module.py
digout/_utils/path.py
digout/_utils/resources.py
digout/_utils/std.py
digout/bookkeeping/__init__.py
digout/bookkeeping/_dirac.py
digout/bookkeeping/_info.py
digout/bookkeeping/produce.py
digout/conf/__init__.py
digout/conf/base/default.yaml
digout/conf/base/user.yaml
digout/conf/prod/input.yaml
digout/conf/prod/root2df.yaml
digout/config/__init__.py
digout/config/_context.py
digout/config/_io.py
digout/config/_version.py
digout/config/step.py
digout/config/workflow.py
digout/context/__init__.py
digout/context/_context.py
digout/core/__init__.py
digout/core/context.py
digout/core/orchestrator.py
digout/core/runner.py
digout/core/scheduler.py
digout/core/step.py
digout/core/stream.py
digout/core/_graph/__init__.py
digout/core/_graph/base.py
digout/core/_graph/build.py
digout/core/_graph/reduce.py
digout/core/_graph/split.py
digout/core/_graph/validate.py
digout/core/workflow/__init__.py
digout/core/workflow/_base.py
digout/core/workflow/_chunk.py
digout/core/workflow/_generic.py
digout/core/workflow/_run.py
digout/dfio/__init__.py
digout/dfio/_base.py
digout/dfio/_csv.py
digout/dfio/_extension.py
digout/dfio/_feather.py
digout/dfio/_parquet.py
digout/environment/__init__.py
digout/environment/_base.py
digout/environment/_conda.py
digout/environment/_dirac.py
digout/environment/_run.py
digout/orchestrator/__init__.py
digout/orchestrator/debug.py
digout/orchestrator/simple.py
digout/registry/__init__.py
digout/registry/_key.py
digout/registry/_registries.py
digout/registry/_registry.py
digout/root2df/__init__.py
digout/root2df/_conversion.py
digout/root2df/_dfname.py
digout/root2df/_validation.py
digout/root2df/_writing.py
digout-0.1.3.dist-info/METADATA
digout-0.1.3.dist-info/WHEEL
digout-0.1.3.dist-info/entry_points.txt
digout-0.1.3.dist-info/licenses/LICENSE
digout-0.1.3.dist-info/RECORD
