Metadata-Version: 2.4
Name: digout
Version: 0.1.3
Summary: Pipeline framework to dump analysis-ready data from LHCb grid-based files
Project-URL: Homepage, https://gitlab.cern.ch/particlepredatorinvasion/digout
Project-URL: Documentation, https://digout.docs.cern.ch
Project-URL: Repository, https://gitlab.cern.ch/particlepredatorinvasion/digout
Project-URL: Issues, https://gitlab.cern.ch/particlepredatorinvasion/digout/issues
Project-URL: Changelog, https://gitlab.cern.ch/particlepredatorinvasion/digout/-/blob/master/CHANGELOG.md
Author-email: anthonyc <anthony.correia@cern.ch>
License: Apache License (2.0)
License-File: LICENSE
Keywords: DAG,cern,computation,graph,grid,lhcb,pipeline,workflow
Classifier: Development Status :: 4 - Beta
Classifier: Intended Audience :: Science/Research
Classifier: License :: OSI Approved :: Apache Software License
Classifier: Operating System :: OS Independent
Classifier: Programming Language :: Python :: 3
Classifier: Programming Language :: Python :: 3 :: Only
Classifier: Programming Language :: Python :: 3.11
Classifier: Programming Language :: Python :: 3.12
Classifier: Programming Language :: Python :: 3.13
Classifier: Topic :: Scientific/Engineering
Requires-Python: >=3.11
Requires-Dist: click>=8.2.1
Requires-Dist: networkx>=3.5
Requires-Dist: omegaconf>=2.3.0
Requires-Dist: pydantic>=2.11.7
Requires-Dist: tqdm>=4.67.1
Provides-Extra: fastparquet
Requires-Dist: fastparquet>=2024.11.0; extra == 'fastparquet'
Provides-Extra: root2df
Requires-Dist: pandas>=2.3.1; extra == 'root2df'
Requires-Dist: pandera[mypy]>=0.25.0; extra == 'root2df'
Requires-Dist: pyarrow>=20.0.0; extra == 'root2df'
Requires-Dist: uproot>=5.6.3; extra == 'root2df'
